geo_auto_install/__init__.py
geo_auto_install/autoinstall.py
geo_auto_install/geo_action.py
geo_auto_install/geo_check.py
geo_auto_install/geo_clean.py
geo_auto_install/geo_config.py
geo_auto_install/geo_download.py
geo_auto_install/geo_enable.py
geo_auto_install/geo_signal.py
geo_auto_install/geo_update.py
geo_auto_install/geo_versions.py
geo_auto_install/utils/__init__.py
geo_auto_install/utils/g_common.py
geo_auto_install/utils/g_fs.py
geo_auto_install/utils/g_http.py
geo_auto_install/utils/g_logger.py
geo_auto_install/utils/g_nextcloud.py
geo_auto_install/utils/g_os.py
geo_auto_install/utils/g_utils.py
test/__init__.py
test/test_common.py
test/test_g_fs.py
test/test_g_http.py
test/test_g_os.py
test/test_g_utils.py
test/test_geo_download.py
test/test_geo_update.py
test/test_geo_versions.py
tuxcy_test-0.0.2.dist-info/METADATA
tuxcy_test-0.0.2.dist-info/WHEEL
tuxcy_test-0.0.2.dist-info/entry_points.txt
tuxcy_test-0.0.2.dist-info/top_level.txt
tuxcy_test-0.0.2.dist-info/RECORD
