Metadata-Version: 2.1
Name: tuxcy-test
Version: 0.0.2
Requires-Dist: requests
Requires-Dist: click
